ideal_ukpostcode/__init__.py
ideal_ukpostcode/exceptions.py
ideal_ukpostcode/pc_format.py
ideal_ukpostcode/pc_validate.py
ideal_ukpostcode-1.0.2.dist-info/LICENSE
ideal_ukpostcode-1.0.2.dist-info/METADATA
ideal_ukpostcode-1.0.2.dist-info/WHEEL
ideal_ukpostcode-1.0.2.dist-info/top_level.txt
ideal_ukpostcode-1.0.2.dist-info/RECORD
