Metadata-Version: 2.1
Name: ideal_ukpostcode
Version: 1.0.2
Summary: package supports validating and formatting postcodes for the UK
Home-page: https://github.com/myselfdesai/ideal_ukpostcode
Author: AMAR DESAI
Author-email: amardesai.bgm@gmail.com
License: MIT license
Keywords: ideal_ukpostcode
Platform: UNKNOWN
Classifier: Development Status :: 2 - Pre-Alpha
Classifier: Intended Audience :: Developers
Classifier: License :: OSI Approved :: MIT License
Classifier: Natural Language :: English
Classifier: Programming Language :: Python :: 3.6
Classifier: Programming Language :: Python :: 3.7
Classifier: Programming Language :: Python :: 3.8
Classifier: Programming Language :: Python :: 3.9
Requires-Python: >=3.6
License-File: LICENSE
